quri_parts/circuit/NOTICE
quri_parts/circuit/__init__.py
quri_parts/circuit/circuit.py
quri_parts/circuit/circuit_linear_mapped.py
quri_parts/circuit/circuit_parametric.py
quri_parts/circuit/clifford_gate.py
quri_parts/circuit/gate.py
quri_parts/circuit/gate_names.py
quri_parts/circuit/gates.py
quri_parts/circuit/inverse.py
quri_parts/circuit/noise/__init__.py
quri_parts/circuit/noise/noise_instruction.py
quri_parts/circuit/noise/noise_model.py
quri_parts/circuit/parameter.py
quri_parts/circuit/parameter_mapping.py
quri_parts/circuit/parameter_shift.py
quri_parts/circuit/py.typed
quri_parts/circuit/topology/__init__.py
quri_parts/circuit/topology/square_lattice.py
quri_parts/circuit/transpile/__init__.py
quri_parts/circuit/transpile/clifford_approximation.py
quri_parts/circuit/transpile/fuse.py
quri_parts/circuit/transpile/gate_kind_decomposer.py
quri_parts/circuit/transpile/identity_manipulation.py
quri_parts/circuit/transpile/multi_pauli_decomposer.py
quri_parts/circuit/transpile/qubit_remapping.py
quri_parts/circuit/transpile/transpiler.py
quri_parts/circuit/transpile/unitary_matrix_decomposer.py
quri_parts/circuit/utils/circuit_drawer.py
quri_parts/circuit/utils/controlled_rotations.py
quri_parts_circuit-17.0.0.dist-info/LICENSE
quri_parts_circuit-17.0.0.dist-info/METADATA
quri_parts_circuit-17.0.0.dist-info/WHEEL
quri_parts_circuit-17.0.0.dist-info/RECORD
